ccui/__init__.py
ccui/__main__.py
ccui/constants.py
ccui/errors.py
ccui/main.py
ccui/tools/__init__.py
ccui/util.py
ccui/utils/__init__.py
ccui/utils/ccui_logo.txt
ccui/utils/ccui_prompt_help.txt
ccui/utils/ccui_tools.txt
ccui-0.2.5.dist-info/WHEEL
ccui-0.2.5.dist-info/METADATA
ccui-0.2.5.dist-info/RECORD
