Metadata-Version: 2.1
Name: ccui
Version: 0.2.5
Summary: CatOw's Console User Interface - An interactive Console of tools
License: GPL-3.0-or-later
Author: CatOw
Author-email: ccuiproject@gmail.com
Requires-Python: >=3.9,<4.0
Classifier: License :: OSI Approved :: GNU General Public License v3 or later (GPLv3+)
Classifier: Programming Language :: Python :: 3
Classifier: Programming Language :: Python :: 3.10
Classifier: Programming Language :: Python :: 3.9
Requires-Dist: rich (>=10.16.1,<11.0.0)
